<Bindings>
	<Binding name="UBERHEAL_TOP3" description="Toggle Announcing of Heals" header="UBERHEAL_HEADER">
		UberHealAnnounce();
	</Binding>
	<Binding name="UBERHEAL_MIDDLE3" description="Toggle Verbose mode" header="UBERHEAL_HEADER">
		UberHealVerboseMode();
	</Binding>
	<Binding name="UBERHEAL_BOTTOM3" description="Open Options Window" header="UBERHEAL_HEADER">
		UberHealVerboseMode();
	</Binding>
	<Binding name="UBERHEAL_TOP" description="Cast Spell 1" header="UBERHEAL_HEADER">
		BuildTargetTables(1,1);
	</Binding>
	<Binding name="UBERHEAL_MIDDLE" description="Cast Spell 2" header="UBERHEAL_HEADER">
		BuildTargetTables(2,1);
	</Binding>
	<Binding name="UBERHEAL_BOTTOM" description="Cast Spell 3" header="UBERHEAL_HEADER">
		BuildTargetTables(3,1);
	</Binding>
	<Binding name="UBERHEAL_BOTTOMER" description="Cast Spell 4" header="UBERHEAL_HEADER">
		BuildTargetTables(4,1);
	</Binding>
	<Binding name="UBERHEAL_BOTTOMEST" description="Cast Spell 5" header="UBERHEAL_HEADER">
		BuildTargetTables(5,1);
	</Binding>
	<Binding name="UBERHEAL_TOP2" description="Cast Spell 1" header="UBERHEAL_HEADER">
		BuildTargetTables(1,2);
	</Binding>
	<Binding name="UBERHEAL_MIDDLE2" description="Cast Spell 2" header="UBERHEAL_HEADER">
		BuildTargetTables(2,2);
	</Binding>
	<Binding name="UBERHEAL_BOTTOM2" description="Cast Spell 3" header="UBERHEAL_HEADER">
		BuildTargetTables(3,2);
	</Binding>
	<Binding name="UBERHEAL_BOTTOMER2" description="Cast Spell 4" header="UBERHEAL_HEADER">
		BuildTargetTables(4,2);
	</Binding>
	<Binding name="UBERHEAL_BOTTOMEST2" description="Cast Spell 5" header="UBERHEAL_HEADER">
		BuildTargetTables(5,2);
	</Binding>

</Bindings>